finhelp/__init__.py
finhelp/finhelp.py
finhelp-0.0.1.dist-info/LICENSE
finhelp-0.0.1.dist-info/METADATA
finhelp-0.0.1.dist-info/WHEEL
finhelp-0.0.1.dist-info/top_level.txt
finhelp-0.0.1.dist-info/RECORD
