Metadata-Version: 2.1
Name: finhelp
Version: 0.0.1
Summary: A python package that streamlines financial calculations
Home-page: https://github.com/kirtish16/finhelp
Author: Kirtish Surangalikar
Project-URL: Bug Tracker, https://github.com/kirtish16/finhelp/issues
Keywords: finance,math,calculations
Classifier: Programming Language :: Python :: 3
Classifier: License :: OSI Approved :: MIT License
Classifier: Operating System :: OS Independent
Requires-Python: >=3.6
License-File: LICENSE
